[
  {
    "slug": "aws-certified-cloud-practitioner",
    "job_postings_7d": 0,
    "job_postings_30d": 0
  },
  {
    "slug": "aws-certified-solutions-architect-associate",
    "job_postings_7d": 0,
    "job_postings_30d": 0
  },
  {
    "slug": "aws-certified-developer-associate",
    "job_postings_7d": 0,
    "job_postings_30d": 0
  },
  {
    "slug": "aws-certified-sysops-administrator-associate",
    "job_postings_7d": 0,
    "job_postings_30d": 0
  },
  {
    "slug": "aws-certified-solutions-architect-professional",
    "job_postings_7d": 0,
    "job_postings_30d": 0
  },
  {
    "slug": "microsoft-azure-fundamentals",
    "job_postings_7d": 0,
    "job_postings_30d": 0
  },
  {
    "slug": "microsoft-azure-administrator-associate",
    "job_postings_7d": 0,
    "job_postings_30d": 0
  },
  {
    "slug": "microsoft-azure-solutions-architect-expert",
    "job_postings_7d": 0,
    "job_postings_30d": 0
  },
  {
    "slug": "google-cloud-digital-leader",
    "job_postings_7d": 0,
    "job_postings_30d": 0
  },
  {
    "slug": "google-cloud-professional-cloud-architect",
    "job_postings_7d": 0,
    "job_postings_30d": 0
  },
  {
    "slug": "google-cloud-professional-data-engineer",
    "job_postings_7d": 0,
    "job_postings_30d": 0
  },
  {
    "slug": "comptia-security",
    "job_postings_7d": 0,
    "job_postings_30d": 0
  },
  {
    "slug": "comptia-network",
    "job_postings_7d": 0,
    "job_postings_30d": 0
  },
  {
    "slug": "comptia-a",
    "job_postings_7d": 0,
    "job_postings_30d": 0
  },
  {
    "slug": "project-management-professional-pmp",
    "job_postings_7d": 0,
    "job_postings_30d": 0
  },
  {
    "slug": "certified-associate-in-project-management-capm",
    "job_postings_7d": 0,
    "job_postings_30d": 0
  },
  {
    "slug": "cisco-certified-network-associate-ccna",
    "job_postings_7d": 0,
    "job_postings_30d": 0
  },
  {
    "slug": "cisco-certified-network-professional-ccnp",
    "job_postings_7d": 0,
    "job_postings_30d": 0
  },
  {
    "slug": "nclex-rn-ncsbn",
    "job_postings_7d": 0,
    "job_postings_30d": 0
  },
  {
    "slug": "cic-certification-in-infection-control-cbic",
    "job_postings_7d": 0,
    "job_postings_30d": 0
  },
  {
    "slug": "ccrn-critical-care-registered-nurse-aacn",
    "job_postings_7d": 0,
    "job_postings_30d": 0
  },
  {
    "slug": "fnp-c-family-nurse-practitioner-ancc",
    "job_postings_7d": 0,
    "job_postings_30d": 0
  },
  {
    "slug": "nremt-p-national-registry-paramedic-nremt",
    "job_postings_7d": 0,
    "job_postings_30d": 0
  },
  {
    "slug": "arrt-american-registry-of-radiologic-technologists-arrt",
    "job_postings_7d": 0,
    "job_postings_30d": 0
  },
  {
    "slug": "crt-certified-respiratory-therapist-nbrc",
    "job_postings_7d": 0,
    "job_postings_30d": 0
  },
  {
    "slug": "pharmd-doctor-of-pharmacy-nabp",
    "job_postings_7d": 0,
    "job_postings_30d": 0
  },
  {
    "slug": "cpht-certified-pharmacy-technician-ptcb",
    "job_postings_7d": 0,
    "job_postings_30d": 0
  },
  {
    "slug": "cph-certified-in-public-health-nbphe",
    "job_postings_7d": 0,
    "job_postings_30d": 0
  },
  {
    "slug": "cfa-level-i-cfa-institute",
    "job_postings_7d": 0,
    "job_postings_30d": 0
  },
  {
    "slug": "cfa-level-ii-cfa-institute",
    "job_postings_7d": 0,
    "job_postings_30d": 0
  },
  {
    "slug": "cfa-level-iii-cfa-institute",
    "job_postings_7d": 0,
    "job_postings_30d": 0
  },
  {
    "slug": "frm-part-i-garp",
    "job_postings_7d": 0,
    "job_postings_30d": 0
  },
  {
    "slug": "frm-part-ii-garp",
    "job_postings_7d": 0,
    "job_postings_30d": 0
  },
  {
    "slug": "cpa-state-boards-nasba",
    "job_postings_7d": 0,
    "job_postings_30d": 0
  },
  {
    "slug": "cma-certified-management-accountant-ima",
    "job_postings_7d": 0,
    "job_postings_30d": 0
  },
  {
    "slug": "cia-certified-internal-auditor-iia",
    "job_postings_7d": 0,
    "job_postings_30d": 0
  },
  {
    "slug": "cisa-certified-information-systems-auditor-isaca",
    "job_postings_7d": 0,
    "job_postings_30d": 0
  },
  {
    "slug": "cfp-certified-financial-planner-cfp-board",
    "job_postings_7d": 0,
    "job_postings_30d": 0
  },
  {
    "slug": "cams-certified-anti-money-laundering-specialist-acams",
    "job_postings_7d": 0,
    "job_postings_30d": 0
  },
  {
    "slug": "ea-enrolled-agent-irs",
    "job_postings_7d": 0,
    "job_postings_30d": 0
  },
  {
    "slug": "aws-d1-1-structural-welding-code-american-welding-society",
    "job_postings_7d": 0,
    "job_postings_30d": 0
  },
  {
    "slug": "nccer-electrical-level-1-nccer",
    "job_postings_7d": 0,
    "job_postings_30d": 0
  },
  {
    "slug": "nccer-electrical-level-2-nccer",
    "job_postings_7d": 0,
    "job_postings_30d": 0
  },
  {
    "slug": "journeyman-electrician-state-licensing-boards",
    "job_postings_7d": 0,
    "job_postings_30d": 0
  },
  {
    "slug": "master-electrician-state-licensing-boards",
    "job_postings_7d": 0,
    "job_postings_30d": 0
  },
  {
    "slug": "epa-section-608-universal-epa",
    "job_postings_7d": 0,
    "job_postings_30d": 0
  },
  {
    "slug": "nate-ice-certification-nate",
    "job_postings_7d": 0,
    "job_postings_30d": 0
  },
  {
    "slug": "hvac-excellence-employment-ready-hvac-excellence",
    "job_postings_7d": 0,
    "job_postings_30d": 0
  },
  {
    "slug": "ase-a1-engine-repair-ase",
    "job_postings_7d": 0,
    "job_postings_30d": 0
  },
  {
    "slug": "ase-master-automotive-technician-ase",
    "job_postings_7d": 0,
    "job_postings_30d": 0
  },
  {
    "slug": "osha-10-hour-construction-osha",
    "job_postings_7d": 0,
    "job_postings_30d": 0
  },
  {
    "slug": "osha-30-hour-construction-osha",
    "job_postings_7d": 0,
    "job_postings_30d": 0
  }
]